svd/__init__.py
svd/__main__.py
svd/_bindings.py
svd/_device.py
svd/bindings.py
svd/device.py
svd/errors.py
svd/memory_block.py
svd/parsing.py
svd/path.py
svd/profiling.py
svd/py.typed
svd/util.py
svada-2.2.1.dist-info/METADATA
svada-2.2.1.dist-info/WHEEL
svada-2.2.1.dist-info/entry_points.txt
svada-2.2.1.dist-info/licenses/LICENSE
svada-2.2.1.dist-info/RECORD
