Metadata-Version: 2.3
Name: svada
Version: 2.2.1
Summary: SVD parsing for Python.
Project-URL: homepage, https://github.com/nordicsemiconductor/svada
Project-URL: repository, https://github.com/nordicsemiconductor/svada.git
Author: Nordic Semiconductor ASA
License: 
Classifier: Development Status :: 5 - Production/Stable
Classifier: License :: OSI Approved :: Apache Software License
Classifier: Programming Language :: Python :: 3
Classifier: Topic :: Software Development :: Build Tools
Requires-Python: >=3.10
Requires-Dist: lxml>=5.3
Requires-Dist: numpy~=2.1
Requires-Dist: typing-extensions>=4.4.0
Provides-Extra: cli
Requires-Dist: intelhex; extra == 'cli'
Requires-Dist: tomlkit; extra == 'cli'
